{
  "en": {
    "localeString": "en-US",
    "latitude": "latitude",
    "longitude": "longitude",
    "placeholder": "Try: place name or -40, 170",
    "wind": "Wind",
    "mph": "mph",
    "humidity": "Humidity",
    "feelsLike": "Feels, like",
    "weekday": ["Sunday", "Monday", "Tuesday", "Wednesday", "Thursday", "Friday", "Saturday"],
    "months": [
      "January",
      "February",
      "March",
      "April",
      "May",
      "June",
      "July",
      "August",
      "September",
      "October",
      "November",
      "December"
    ],
    "country": {
      "BD": "Bangladesh",
      "BE": "Belgium",
      "BF": "Burkina Faso",
      "BG": "Bulgaria",
      "BA": "Bosnia and Herzegovina",
      "BB": "Barbados",
      "WF": "Wallis and Futuna",
      "BL": "Saint Barthelemy",
      "BM": "Bermuda",
      "BN": "Brunei",
      "BO": "Bolivia",
      "BH": "Bahrain",
      "BI": "Burundi",
      "BJ": "Benin",
      "BT": "Bhutan",
      "JM": "Jamaica",
      "BV": "Bouvet Island",
      "BW": "Botswana",
      "WS": "Samoa",
      "BQ": "Bonaire, Saint Eustatius and Saba ",
      "BR": "Brazil",
      "BS": "Bahamas",
      "JE": "Jersey",
      "BY": "Belarus",
      "BZ": "Belize",
      "RU": "Russia",
      "RW": "Rwanda",
      "RS": "Serbia",
      "TL": "East Timor",
      "RE": "Reunion",
      "TM": "Turkmenistan",
      "TJ": "Tajikistan",
      "RO": "Romania",
      "TK": "Tokelau",
      "GW": "Guinea-Bissau",
      "GU": "Guam",
      "GT": "Guatemala",
      "GS": "South Georgia and the South Sandwich Islands",
      "GR": "Greece",
      "GQ": "Equatorial Guinea",
      "GP": "Guadeloupe",
      "JP": "Japan",
      "GY": "Guyana",
      "GG": "Guernsey",
      "GF": "French Guiana",
      "GE": "Georgia",
      "GD": "Grenada",
      "GB": "United Kingdom",
      "GA": "Gabon",
      "SV": "El Salvador",
      "GN": "Guinea",
      "GM": "Gambia",
      "GL": "Greenland",
      "GI": "Gibraltar",
      "GH": "Ghana",
      "OM": "Oman",
      "TN": "Tunisia",
      "JO": "Jordan",
      "HR": "Croatia",
      "HT": "Haiti",
      "HU": "Hungary",
      "HK": "Hong Kong",
      "HN": "Honduras",
      "HM": "Heard Island and McDonald Islands",
      "VE": "Venezuela",
      "PR": "Puerto Rico",
      "PS": "Palestinian Territory",
      "PW": "Palau",
      "PT": "Portugal",
      "SJ": "Svalbard and Jan Mayen",
      "PY": "Paraguay",
      "IQ": "Iraq",
      "PA": "Panama",
      "PF": "French Polynesia",
      "PG": "Papua New Guinea",
      "PE": "Peru",
      "PK": "Pakistan",
      "PH": "Philippines",
      "PN": "Pitcairn",
      "PL": "Poland",
      "PM": "Saint Pierre and Miquelon",
      "ZM": "Zambia",
      "EH": "Western Sahara",
      "EE": "Estonia",
      "EG": "Egypt",
      "ZA": "South Africa",
      "EC": "Ecuador",
      "IT": "Italy",
      "VN": "Vietnam",
      "SB": "Solomon Islands",
      "ET": "Ethiopia",
      "SO": "Somalia",
      "ZW": "Zimbabwe",
      "SA": "Saudi Arabia",
      "ES": "Spain",
      "ER": "Eritrea",
      "ME": "Montenegro",
      "MD": "Moldova",
      "MG": "Madagascar",
      "MF": "Saint Martin",
      "MA": "Morocco",
      "MC": "Monaco",
      "UZ": "Uzbekistan",
      "MM": "Myanmar",
      "ML": "Mali",
      "MO": "Macao",
      "MN": "Mongolia",
      "MH": "Marshall Islands",
      "MK": "Macedonia",
      "MU": "Mauritius",
      "MT": "Malta",
      "MW": "Malawi",
      "MV": "Maldives",
      "MQ": "Martinique",
      "MP": "Northern Mariana Islands",
      "MS": "Montserrat",
      "MR": "Mauritania",
      "IM": "Isle of Man",
      "UG": "Uganda",
      "TZ": "Tanzania",
      "MY": "Malaysia",
      "MX": "Mexico",
      "IL": "Israel",
      "FR": "France",
      "IO": "British Indian Ocean Territory",
      "SH": "Saint Helena",
      "FI": "Finland",
      "FJ": "Fiji",
      "FK": "Falkland Islands",
      "FM": "Micronesia",
      "FO": "Faroe Islands",
      "NI": "Nicaragua",
      "NL": "Netherlands",
      "NO": "Norway",
      "NA": "Namibia",
      "VU": "Vanuatu",
      "NC": "New Caledonia",
      "NE": "Niger",
      "NF": "Norfolk Island",
      "NG": "Nigeria",
      "NZ": "New Zealand",
      "NP": "Nepal",
      "NR": "Nauru",
      "NU": "Niue",
      "CK": "Cook Islands",
      "XK": "Kosovo",
      "CI": "Ivory Coast",
      "CH": "Switzerland",
      "CO": "Colombia",
      "CN": "China",
      "CM": "Cameroon",
      "CL": "Chile",
      "CC": "Cocos Islands",
      "CA": "Canada",
      "CG": "Republic of the Congo",
      "CF": "Central African Republic",
      "CD": "Democratic Republic of the Congo",
      "CZ": "Czech Republic",
      "CY": "Cyprus",
      "CX": "Christmas Island",
      "CR": "Costa Rica",
      "CW": "Curacao",
      "CV": "Cape Verde",
      "CU": "Cuba",
      "SZ": "Swaziland",
      "SY": "Syria",
      "SX": "Sint Maarten",
      "KG": "Kyrgyzstan",
      "KE": "Kenya",
      "SS": "South Sudan",
      "SR": "Suriname",
      "KI": "Kiribati",
      "KH": "Cambodia",
      "KN": "Saint Kitts and Nevis",
      "KM": "Comoros",
      "ST": "Sao Tome and Principe",
      "SK": "Slovakia",
      "KR": "South Korea",
      "SI": "Slovenia",
      "KP": "North Korea",
      "KW": "Kuwait",
      "SN": "Senegal",
      "SM": "San Marino",
      "SL": "Sierra Leone",
      "SC": "Seychelles",
      "KZ": "Kazakhstan",
      "KY": "Cayman Islands",
      "SG": "Singapore",
      "SE": "Sweden",
      "SD": "Sudan",
      "DO": "Dominican Republic",
      "DM": "Dominica",
      "DJ": "Djibouti",
      "DK": "Denmark",
      "VG": "British Virgin Islands",
      "DE": "Germany",
      "YE": "Yemen",
      "DZ": "Algeria",
      "US": "United States",
      "UY": "Uruguay",
      "YT": "Mayotte",
      "UM": "United States Minor Outlying Islands",
      "LB": "Lebanon",
      "LC": "Saint Lucia",
      "LA": "Laos",
      "TV": "Tuvalu",
      "TW": "Taiwan",
      "TT": "Trinidad and Tobago",
      "TR": "Turkey",
      "LK": "Sri Lanka",
      "LI": "Liechtenstein",
      "LV": "Latvia",
      "TO": "Tonga",
      "LT": "Lithuania",
      "LU": "Luxembourg",
      "LR": "Liberia",
      "LS": "Lesotho",
      "TH": "Thailand",
      "TF": "French Southern Territories",
      "TG": "Togo",
      "TD": "Chad",
      "TC": "Turks and Caicos Islands",
      "LY": "Libya",
      "VA": "Vatican",
      "VC": "Saint Vincent and the Grenadines",
      "AE": "United Arab Emirates",
      "AD": "Andorra",
      "AG": "Antigua and Barbuda",
      "AF": "Afghanistan",
      "AI": "Anguilla",
      "VI": "U.S. Virgin Islands",
      "IS": "Iceland",
      "IR": "Iran",
      "AM": "Armenia",
      "AL": "Albania",
      "AO": "Angola",
      "AQ": "Antarctica",
      "AS": "American Samoa",
      "AR": "Argentina",
      "AU": "Australia",
      "AT": "Austria",
      "AW": "Aruba",
      "IN": "India",
      "AX": "Aland Islands",
      "AZ": "Azerbaijan",
      "IE": "Ireland",
      "ID": "Indonesia",
      "UA": "Ukraine",
      "QA": "Qatar",
      "MZ": "Mozambique"
    }
  },
  "be": {
    "localeString": "be-BY",
    "latitude": "Шырата",
    "longitude": "Даўгата",
    "placeholder": "Увядзіце месца ці каардынаты праз коску",
    "wind": "Вецер",
    "mph": "міля/г",
    "humidity": "Вільготнасць",
    "feelsLike": "Адчуваецца, як",
    "weekday": ["Нядзеля", "Панядзелак", "Чацвер", "Асяроддзе", "Чацвер", "Пятнiца", "Субота"],
    "months": [
      "студзень",
      "люты",
      "сакавік",
      "красавік",
      "травень",
      "чэрвень",
      "ліпень",
      "жнівень",
      "верасень",
      "кастрычнік",
      "лістапад",
      "снежань"
    ],
    "country": {
      "BD": "Бангладэш",
      "BE": "Бельгія",
      "BF": "Буркіна-Фасо",
      "BG": "Балгарыя",
      "BA": "Боснія і Герцагавіна",
      "BB": "Барбадас",
      "WF": "Уоліс і Футуна",
      "BL": "Святы Варфелемій",
      "BM": "Бермуды",
      "BN": "Бруней",
      "BO": "Балівія",
      "BH": "Бахрэйн",
      "BI": "Бурундзі",
      "BJ": "Бенін",
      "BT": "Бутан",
      "JM": "Ямайка",
      "BV": "Востраў Буве",
      "BW": "Батсвана",
      "WS": "Самоа",
      "BQ": "Банайер, святы Яўстафій і Саба ",
      "BR": "Бразілія",
      "BS": "Багамскія астравы",
      "JE": "Джэрсі",
      "BY": "Беларусь",
      "BZ": "Беліз",
      "RU": "Расія",
      "RW": "Руандзе",
      "RS": "Сербія",
      "TL": "Усходні Тымор",
      "RE": "Уз'яднанне",
      "TM": "Туркменістан",
      "TJ": "Таджыкістан",
      "RO": "Румынія",
      "TK": "Такелаў",
      "GW": "Гвінея-Бісаў",
      "GU": "Гуам",
      "GT": "Гватэмала",
      "GS": "Паўднёвая Джорджыя і Паўднёвыя астравы Сэндвіч",
      "GR": "Грэцыя",
      "GQ": "Экватарыяльная Гвінея",
      "GP": "Гвадэлупа",
      "JP": "Японія",
      "GY": "Гаяна",
      "GG": "Гернсі",
      "GF": "Французская Гвіяна",
      "GE": "Грузія",
      "GD": "Грэнада",
      "GB": "Злучанае Каралеўства",
      "GA": "Габон",
      "SV": "Сальвадор",
      "GN": "Гвінея",
      "GM": "Гамбія",
      "GL": "Грэнландыя",
      "GI": "Гібралтар",
      "GH": "Гана",
      "OM": "Аман",
      "TN": "Туніс",
      "JO": "Іарданія",
      "HR": "Харватыя",
      "HT": "Гаіці",
      "HU": "Венгрыя",
      "HK": "Ганконг",
      "HN": "Гандурас",
      "HM": "Астравы Херд і Макдональд",
      "VE": "Венесуэла",
      "PR": "Пуэрта-Рыка",
      "PS": "Палестынская тэрыторыя",
      "PW": "Палаў",
      "PT": "Партугалія",
      "SJ": "Шпіцберген і Ян Мейен",
      "PY": "Парагвай",
      "IQ": "Ірак",
      "PA": "Панама",
      "PF": "Французская Палінезія",
      "PG": "Папуа-Новая Гвінея",
      "PE": "Перу",
      "PK": "Пакістан",
      "PH": "Філіпіны",
      "PN": "Піткерн",
      "PL": "Польшча",
      "PM": "Сэнт-П'ер і Мікелон",
      "ZM": "Замбія",
      "EH": "Заходняя Сахара",
      "EE": "Эстонія",
      "EG": "Егіпет",
      "ZA": "Паўднёвая Афрыка",
      "EC": "Эквадор",
      "IT": "Італія",
      "VN": "В'етнам",
      "SB": "Саламонавы выспы",
      "ET": "Эфіопія",
      "SO": "Самалі",
      "ZW": "Зімбабвэ",
      "SA": "Саўдаўская Аравія",
      "ES": "Іспанія",
      "ER": "Эрытрэя",
      "ME": "Чарнагорыя",
      "MD": "Малдова",
      "MG": "Мадагаскар",
      "MF": "Святы Марцін",
      "MA": "Марока",
      "MC": "Манака",
      "UZ": "Узбекістан",
      "MM": "М'янма",
      "ML": "Малі",
      "MO": "Макао",
      "MN": "Манголія",
      "MH": "Маршалавы выспы",
      "MK": "Македонія",
      "MU": "Маўрыкій",
      "MT": "Мальта",
      "MW": "Малаві",
      "MV": "Мальдывы",
      "MQ": "Марцініка",
      "MP": "Паўночныя Марыянскія астравы",
      "MS": "Монтсеррат",
      "MR": "Маўрытанія",
      "IM": "Востраў Мэн",
      "UG": "Уганда",
      "TZ": "Танзанія",
      "MY": "Малайзія",
      "MX": "Мексіка",
      "IL": "Ізраіль",
      "FR": "Францыя",
      "IO": "Брытанская тэрыторыя ў Індыйскім акіяне",
      "SH": "Святая Алена",
      "FI": "Фінляндыя",
      "FJ": "Фіджы",
      "FK": "Фолклендскія выспы",
      "FM": "Мікранезія",
      "FO": "Фарэрскія выспы",
      "NI": "Нікарагуа",
      "NL": "Нідэрланды",
      "NO": "Нарвегія",
      "NA": "Намібія",
      "VU": "Вануату",
      "NC": "Новая Каледонія",
      "NE": "Нігер",
      "NF": "Востраў Норфолк",
      "NG": "Нігерыя",
      "NZ": "Новая Зеландыя",
      "NP": "Непал",
      "NR": "Науру",
      "NU": "Ніуэ",
      "CK": "Астравы Кука",
      "XK": "Косава",
      "CI": "Кот-д'Івуар",
      "CH": "Швейцарыя",
      "CO": "Калумбія",
      "CN": "Кітай",
      "CM": "Камерун",
      "CL": "Чылі",
      "CC": "Какосавыя выспы",
      "CA": "Канада",
      "CG": "Рэспубліка Конга",
      "CF": "Цэнтральна-Афрыканская Рэспубліка",
      "CD": "Дэмакратычная Рэспубліка Конга",
      "CZ": "Чэская Рэспубліка",
      "CY": "Кіпр",
      "CX": "Востраў Раства",
      "CR": "Коста-Рыка",
      "CW": "Кюрасао",
      "CV": "Каба-Вэрдэ",
      "CU": "Куба",
      "SZ": "Свазіленд",
      "SY": "Сірыя",
      "SX": "Сінт Маартэн",
      "KG": "Кыргызстан",
      "KE": "Кенія",
      "SS": "Паўднёвы Судан",
      "SR": "Сурынам",
      "KI": "Кірыбаты",
      "KH": "Камбоджа",
      "KN": "Сэнт-Кітс і Нэвіс",
      "KM": "Каморскія выспы",
      "ST": "Сан-Томе і Прынсіпі",
      "SK": "Славакія",
      "KR": "Паўднёвая Карэя",
      "SI": "Славенія",
      "KP": "Паўночная Карэя",
      "KW": "Кувейт",
      "SN": "Сенегал",
      "SM": "Сан-Марына",
      "SL": "Сьера-Леонэ",
      "SC": "Сейшэльскія выспы",
      "KZ": "Казахстан",
      "KY": "Кайманавы выспы",
      "SG": "Сінгапур",
      "SE": "Швецыя",
      "SD": "Судан",
      "DO": "Дамініканская Рэспубліка",
      "DM": "Дамініка",
      "DJ": "Джыбуці",
      "DK": "Данія",
      "VG": "Брытанскія Віргінскія астравы",
      "DE": "Германія",
      "YE": "Емен",
      "DZ": "Алжыр",
      "US": "Злучаныя Штаты",
      "UY": "Уругвай",
      "YT": "Майёта",
      "UM": "Малыя аддаленыя астравы ЗША",
      "LB": "Ліван",
      "LC": "Святая Люцыя",
      "LA": "Лаос",
      "TV": "Тувалу",
      "TW": "Тайвань",
      "TT": "Трынідад і Табага",
      "TR": "Турцыя",
      "LK": "Шры Ланка",
      "LI": "Ліхтэнштэйн",
      "LV": "Латвія",
      "TO": "Тонга",
      "LT": "Літва",
      "LU": "Люксембург",
      "LR": "Ліберыя",
      "LS": "Лесота",
      "TH": "Тайланд",
      "TF": "Паўднёвыя тэрыторыі Францыі",
      "TG": "Ісці",
      "TD": "Чад",
      "TC": "Астравы Тэркс і Кайкас",
      "LY": "Лівія",
      "VA": "Ватыкан",
      "VC": "Сэнт-Вінсэнт і Грэнадыны",
      "AE": "Абяднаныя Арабскія Эміраты",
      "AD": "Андора",
      "AG": "Антыгуа і Барбуда",
      "AF": "Афганістан",
      "AI": "Ангілья",
      "VI": "Амерыканскія Віргінскія выспы",
      "IS": "Ісландыя",
      "IR": "Іран",
      "AM": "Арменія",
      "AL": "Албанія",
      "AO": "Ангола",
      "AQ": "Антарктыда",
      "AS": "Амерыканскае Самоа",
      "AR": "Аргенціна",
      "AU": "Аўстралія",
      "AT": "Аўстрыя",
      "AW": "Аруба",
      "IN": "Індыя",
      "AX": "Аландскія выспы",
      "AZ": "Азербайджан",
      "IE": "Ірландыя",
      "ID": "Інданезія",
      "UA": "Украіна",
      "QA": "Катар",
      "MZ": "Мазамбік"
    }
  },
  "ru": {
    "localeString": "ru-RU",
    "latitude": "Широта",
    "longitude": "Долгота",
    "placeholder": "Введите место или координаты через запятую",
    "wind": "Ветер",
    "mph": "миля/ч",
    "humidity": "Влажность",
    "feelsLike": "Ощущается, как",
    "weekday": ["Воскресенье", "Понедельник", "Вторник", "Среда", "Четверг", "Пятница", "Суббота"],
    "months": [
      "Январь",
      "Февраль",
      "Март",
      "Апрель",
      "Май",
      "Июнь",
      "Июль",
      "Август",
      "Сентябрь",
      "Октябрь",
      "Ноябрь",
      "Декабрь"
    ],
    "country": {
      "BD": "Бангладеш",
      "BE": "Бельгия",
      "BF": "Буркина-Фасо",
      "BG": "Болгария",
      "BA": "Босния и Герцеговина",
      "BB": "Барбадос",
      "WF": "Уоллис и Футуна",
      "BL": "Сен-Бартельми",
      "BM": "Бермудские острова",
      "BN": "Бруней",
      "BO": "Боливия",
      "BH": "Бахрейн",
      "BI": "Бурунди",
      "BJ": "Бенин",
      "BT": "Бутан",
      "JM": "Ямайка",
      "BV": "Остров Буве",
      "BW": "Ботсвана",
      "WS": "Самоа",
      "BQ": "Бонэйр, Синт-Эстатиус и Саба ",
      "BR": "Бразилия",
      "BS": "Багамские о-ва",
      "JE": "Джерси",
      "BY": "Беларусь",
      "BZ": "Белиз",
      "RU": "Россия",
      "RW": "Руанда",
      "RS": "Сербия",
      "TL": "Восточный Тимор",
      "RE": "воссоединение",
      "TM": "Туркменистан",
      "TJ": "Таджикистан",
      "RO": "Румыния",
      "TK": "Токелау",
      "GW": "Гвинея-Бисау",
      "GU": "Гуам",
      "GT": "Гватемала",
      "GS": "Южная Георгия и Южные Сандвичевы острова",
      "GR": "Греция",
      "GQ": "Экваториальная Гвинея",
      "GP": "Гваделупа",
      "JP": "Япония",
      "GY": "Гайана",
      "GG": "шерстяная фуфайка",
      "GF": "Французская Гвиана",
      "GE": "Грузия",
      "GD": "Гренада",
      "GB": "Соединенное Королевство",
      "GA": "Габон",
      "SV": "Сальвадор",
      "GN": "Гвинея",
      "GM": "Гамбия",
      "GL": "Гренландия",
      "GI": "Гибралтар",
      "GH": "Гана",
      "OM": "Оман",
      "TN": "Тунис",
      "JO": "Иордания",
      "HR": "Хорватия",
      "HT": "Гаити",
      "HU": "Венгрия",
      "HK": "Гонконг",
      "HN": "Гондурас",
      "HM": "Острова Херд и Макдональд",
      "VE": "Венесуэла",
      "PR": "Пуэрто-Рико",
      "PS": "Палестинская территория",
      "PW": "Palau",
      "PT": "Португалия",
      "SJ": "Шпицберген и Ян Майен",
      "PY": "Парагвай",
      "IQ": "Ирак",
      "PA": "Панама",
      "PF": "Французская Полинезия",
      "PG": "Папуа - Новая Гвинея",
      "PE": "Перу",
      "PK": "Пакистан",
      "PH": "Филиппины",
      "PN": "Питкэрн",
      "PL": "Польша",
      "PM": "Сен-Пьер и Микелон",
      "ZM": "Замбия",
      "EH": "Западная Сахара",
      "EE": "Эстония",
      "EG": "Египет",
      "ZA": "Южная Африка",
      "EC": "Эквадор",
      "IT": "Италия",
      "VN": "Вьетнам",
      "SB": "Соломоновы острова",
      "ET": "Эфиопия",
      "SO": "Сомали",
      "ZW": "Зимбабве",
      "SA": "Саудовская Аравия",
      "ES": "Испания",
      "ER": "Эритрея",
      "ME": "Черногория",
      "MD": "Молдова",
      "MG": "Мадагаскар",
      "MF": "Святой мартин",
      "MA": "Марокко",
      "MC": "Монако",
      "UZ": "Узбекистан",
      "MM": "Мьянма",
      "ML": "Мали",
      "MO": "Macao",
      "MN": "Монголия",
      "MH": "Маршалловы острова",
      "MK": "Македония",
      "MU": "Маврикий",
      "MT": "Мальта",
      "MW": "Малави",
      "MV": "Мальдивы",
      "MQ": "Мартиника",
      "MP": "Северные Марианские острова",
      "MS": "Монсеррат",
      "MR": "Мавритания",
      "IM": "Остров Мэн",
      "UG": "Уганда",
      "TZ": "Танзания",
      "MY": "Малайзия",
      "MX": "Мексика",
      "IL": "Израиль",
      "FR": "Франция",
      "IO": "Британская территория Индийского океана",
      "SH": "Остров Святой Елены",
      "FI": "Финляндия",
      "FJ": "Фиджи",
      "FK": "Фолклендские острова",
      "FM": "Микронезия",
      "FO": "Фарерские острова",
      "NI": "Никарагуа",
      "NL": "Нидерланды",
      "NO": "Норвегия",
      "NA": "Намибия",
      "VU": "Вануату",
      "NC": "Новая Каледония",
      "NE": "Нигер",
      "NF": "Остров Норфолк",
      "NG": "Нигерия",
      "NZ": "Новая Зеландия",
      "NP": "Непал",
      "NR": "Науру",
      "NU": "Niue",
      "CK": "Острова Кука",
      "XK": "Косово",
      "CI": "Кот-д'Ивуар",
      "CH": "Швейцария",
      "CO": "Колумбия",
      "CN": "Китай",
      "CM": "Камерун",
      "CL": "Чили",
      "CC": "Кокосовые острова",
      "CA": "Канада",
      "CG": "Республика Конго",
      "CF": "Центрально-Африканская Республика",
      "CD": "Демократическая Республика Конго",
      "CZ": "Чехия",
      "CY": "Кипр",
      "CX": "Остров Рождества",
      "CR": "Коста Рика",
      "CW": "ликер кюрасо",
      "CV": "Кабо-Верде",
      "CU": "Куба",
      "SZ": "Свазиленд",
      "SY": "Сирия",
      "SX": "Синт-Мартен",
      "KG": "Киргизия",
      "KE": "Кения",
      "SS": "южный Судан",
      "SR": "Суринам",
      "KI": "Кирибати",
      "KH": "Камбоджа",
      "KN": "Сент-Китс и Невис",
      "KM": "Коморские острова",
      "ST": "Сан-Томе и Принсипи",
      "SK": "Словакия",
      "KR": "Южная Корея",
      "SI": "Словения",
      "KP": "Северная Корея",
      "KW": "Кувейт",
      "SN": "Сенегал",
      "SM": "Сан-Марино",
      "SL": "Сьерра-Леоне",
      "SC": "Сейшельские острова",
      "KZ": "Казахстан",
      "KY": "Каймановы острова",
      "SG": "Сингапур",
      "SE": "Швеция",
      "SD": "Судан",
      "DO": "Доминиканская Респблика",
      "DM": "Доминика",
      "DJ": "Джибути",
      "DK": "Дания",
      "VG": "Британские Виргинские острова",
      "DE": "Германия",
      "YE": "Йемен",
      "DZ": "Алжир",
      "US": "Соединенные Штаты",
      "UY": "Уругвай",
      "YT": "Майотта",
      "UM": "Малые отдаленные острова США",
      "LB": "Ливан",
      "LC": "Сент-Люсия",
      "LA": "Лаос",
      "TV": "Тувалу",
      "TW": "Тайвань",
      "TT": "Тринидад и Тобаго",
      "TR": "индейка",
      "LK": "Шри-Ланка",
      "LI": "Лихтенштейн",
      "LV": "Латвия",
      "TO": "Тонга",
      "LT": "Литва",
      "LU": "Люксембург",
      "LR": "Либерия",
      "LS": "Лесото",
      "TH": "Таиланд",
      "TF": "Южные Французские Территории",
      "TG": "Идти",
      "TD": "Чад",
      "TC": "Острова Теркс и Кайкос",
      "LY": "Ливия",
      "VA": "Ватикан",
      "VC": "Святой Винсент и Гренадины",
      "AE": "Объединенные Арабские Эмираты",
      "AD": "андорра",
      "AG": "Антигуа и Барбуда",
      "AF": "Афганистан",
      "AI": "Ангилья",
      "VI": "США Виргинские острова",
      "IS": "Исландия",
      "IR": "Иран",
      "AM": "Армения",
      "AL": "Албания",
      "AO": "Ангола",
      "AQ": "Антарктида",
      "AS": "американское Самоа",
      "AR": "Аргентина",
      "AU": "Австралия",
      "AT": "Австрия",
      "AW": "Аруба",
      "IN": "Индия",
      "AX": "Аландские острова",
      "AZ": "Азербайджан",
      "IE": "Ирландия",
      "ID": "Индонезия",
      "UA": "Украина",
      "QA": "Катар",
      "MZ": "Мозамбик"
    }
  }
}
